blocks_lmt/__init__.py
blocks_lmt/activity.py
blocks_lmt/azure_servicebus_log_exporter.py
blocks_lmt/azure_servicebus_trace_exporter.py
blocks_lmt/log_config.py
blocks_lmt/tracing.py
seliseblocks_lmt-0.0.3.dist-info/METADATA
seliseblocks_lmt-0.0.3.dist-info/WHEEL
seliseblocks_lmt-0.0.3.dist-info/RECORD
