Metadata-Version: 2.4
Name: seliseblocks-lmt
Version: 0.0.3
Summary: Logging, Monitoring, and Tracing library for Selise Blocks applications using Azure Service Bus.
Project-URL: Homepage, https://github.com/SELISEdigitalplatforms/l0-py-blocks-genesis
Project-URL: Repository, https://github.com/SELISEdigitalplatforms/l0-py-blocks-genesis
Author-email: Selise Blocks <mostafizur.rahman@selisegroup.com>
Keywords: Azure Service Bus,LMT,Logging,Monitoring,OpenTelemetry,Selise,Selise Blocks,Tracing
Requires-Python: >=3.9
Requires-Dist: azure-servicebus>=7.14.2
Requires-Dist: opentelemetry-api>=1.33.1
Requires-Dist: opentelemetry-instrumentation-fastapi>=0.54b1
Requires-Dist: opentelemetry-sdk>=1.33.1
